[
  {
    "label": "CORE",
    "items": [
      {
        "label": "Core Package",
        "slug": "api/core"
      },
      {
        "label": "Base",
        "slug": "api/core/base"
      },
      {
        "label": "CivilianVehicles enum",
        "slug": "api/core/civilianvehicles"
      },
      {
        "label": "Client",
        "slug": "api/core/client"
      },
      {
        "label": "ClientEvents",
        "slug": "api/core/clientevents"
      },
      {
        "label": "ClientOptions",
        "slug": "api/core/clientoptions"
      },
      {
        "label": "CommandLog",
        "slug": "api/core/commandlog"
      },
      {
        "label": "CommandLogManager",
        "slug": "api/core/commandlogmanager"
      },
      {
        "label": "CommandManager",
        "slug": "api/core/commandmanager"
      },
      {
        "label": "convertToPascalCase() function",
        "slug": "api/core/converttopascalcase"
      },
      {
        "label": "DepartmentOfTransportationVehicles enum",
        "slug": "api/core/departmentoftransportationvehicles"
      },
      {
        "label": "EmergencyCall",
        "slug": "api/core/emergencycall"
      },
      {
        "label": "EmergencyCallManager",
        "slug": "api/core/emergencycallmanager"
      },
      {
        "label": "ERLCEvents enum",
        "slug": "api/core/erlcevents"
      },
      {
        "label": "FireRescueVehicles enum",
        "slug": "api/core/firerescuevehicles"
      },
      {
        "label": "InvalidServerKeyError",
        "slug": "api/core/invalidserverkeyerror"
      },
      {
        "label": "JobVehicles enum",
        "slug": "api/core/jobvehicles"
      },
      {
        "label": "KillLog",
        "slug": "api/core/killlog"
      },
      {
        "label": "KillLogManager",
        "slug": "api/core/killlogmanager"
      },
      {
        "label": "LawEnforcementVehicles enum",
        "slug": "api/core/lawenforcementvehicles"
      },
      {
        "label": "ModCall",
        "slug": "api/core/modcall"
      },
      {
        "label": "ModCallManager",
        "slug": "api/core/modcallmanager"
      },
      {
        "label": "Player",
        "slug": "api/core/player"
      },
      {
        "label": "PlayerManager",
        "slug": "api/core/playermanager"
      },
      {
        "label": "RawCommandLog",
        "slug": "api/core/rawcommandlog"
      },
      {
        "label": "RawEmergencyCall",
        "slug": "api/core/rawemergencycall"
      },
      {
        "label": "RawJoinLog",
        "slug": "api/core/rawjoinlog"
      },
      {
        "label": "RawKillLog",
        "slug": "api/core/rawkilllog"
      },
      {
        "label": "RawModCall",
        "slug": "api/core/rawmodcall"
      },
      {
        "label": "RawPlayerData",
        "slug": "api/core/rawplayerdata"
      },
      {
        "label": "RawServerData",
        "slug": "api/core/rawserverdata"
      },
      {
        "label": "RawStaffData",
        "slug": "api/core/rawstaffdata"
      },
      {
        "label": "RawVehicle",
        "slug": "api/core/rawvehicle"
      },
      {
        "label": "RawWebhookEmergencyCall",
        "slug": "api/core/rawwebhookemergencycall"
      },
      {
        "label": "RestManager",
        "slug": "api/core/restmanager"
      },
      {
        "label": "Server",
        "slug": "api/core/server"
      },
      {
        "label": "ServerManager",
        "slug": "api/core/servermanager"
      },
      {
        "label": "Staff",
        "slug": "api/core/staff"
      },
      {
        "label": "StaffManager",
        "slug": "api/core/staffmanager"
      },
      {
        "label": "Vehicle",
        "slug": "api/core/vehicle"
      },
      {
        "label": "VehicleManager",
        "slug": "api/core/vehiclemanager"
      },
      {
        "label": "WebhookServer",
        "slug": "api/core/webhookserver"
      }
    ]
  }
]